fran_calc/__init__.py
fran_calc/__main__.py
fran_calc/fran_calc.py
fran_calc/fran_calc_terminal.py
fran_calc/gui.py
fran_calc/modules.py
fran_calc/calculations/__init__.py
fran_calc/calculations/algebra_equations.py
fran_calc/calculations/basic_math.py
fran_calc/calculations/conversions_units.py
fran_calc/calculations/date_age.py
fran_calc/calculations/date_time.py
fran_calc/calculations/finance.py
fran_calc/calculations/geometry.py
fran_calc/calculations/health.py
fran_calc/calculations/miscellaneous.py
fran_calc/calculations/physics_engineering.py
fran_calc/calculations/probability.py
fran_calc/calculations/validation_indetifiers.py
fran_calculator/__init__.py
fran_calculator/franCalc.py
fran_calculator/modules.py
francalc-0.4.0.dist-info/LICENSE
francalc-0.4.0.dist-info/METADATA
francalc-0.4.0.dist-info/WHEEL
francalc-0.4.0.dist-info/entry_points.txt
francalc-0.4.0.dist-info/top_level.txt
francalc-0.4.0.dist-info/RECORD
