Metadata-Version: 2.1
Name: francalc
Version: 0.4.0
Author: Lukydnomo
License-File: LICENSE
Requires-Dist: requests
Requires-Dist: colorama
Requires-Dist: pyqt5
